flask_firehose.py
Flask_Firehose-0.2.3.dist-info/LICENSE
Flask_Firehose-0.2.3.dist-info/METADATA
Flask_Firehose-0.2.3.dist-info/WHEEL
Flask_Firehose-0.2.3.dist-info/top_level.txt
Flask_Firehose-0.2.3.dist-info/RECORD
