Metadata-Version: 2.1
Name: Flask-Firehose
Version: 0.2.3
Summary: HTTP/2 Server Push for your Flask apps.
Home-page: https://github.com/shreyanshk/flask-firehose
Author: Shreyansh Khajanchi
Author-email: hello@shreyanshja.in
License: MIT
Platform: any
Classifier: Environment :: Web Environment
Classifier: Intended Audience :: Developers
Classifier: License :: OSI Approved :: MIT License
Classifier: Operating System :: OS Independent
Classifier: Programming Language :: Python
Classifier: Topic :: Internet :: WWW/HTTP :: Dynamic Content
Classifier: Topic :: Software Development :: Libraries :: Python Modules
Requires-Dist: Flask (>=0.10)
